setup.py
faa/__init__.py
faa/faa.py
faa.egg-info/PKG-INFO
faa.egg-info/SOURCES.txt
faa.egg-info/dependency_links.txt
faa.egg-info/top_level.txt
faa/api/__init__.py
faa/api/api.py
faa/api/test_api.py
faa/api/xml2dict/__init__.py
faa/api/xml2dict/object_dict.py
faa/api/xml2dict/xml2dict.py