Metadata-Version: 1.0
Name: faa
Version: 1.1
Summary: Python wrapper for the FAA flight APIs.
Home-page: https://github.com/codeforamerica/faa_python
Author: Zach Williams
Author-email: zach@codeforamerica.org
License: BSD
Keywords: FAA,faa,flight api,faa api
Platform: UNKNOWN
Classifier: Development Status :: 5 - Production/Stable
Classifier: Intended Audience :: Developers
Classifier: Natural Language :: English
Classifier: Operating System :: OS Independent
Classifier: Programming Language :: Python :: 2
Classifier: Topic :: Internet
Classifier: Topic :: Internet :: WWW/HTTP
